langchain_ampersend/__init__.py
langchain_ampersend/a2a/__init__.py
langchain_ampersend/a2a/toolkit.py
langchain_ampersend/py.typed
langchain_ampersend-0.0.1.dist-info/WHEEL
langchain_ampersend-0.0.1.dist-info/METADATA
langchain_ampersend-0.0.1.dist-info/RECORD
