Metadata-Version: 2.3
Name: langchain-ampersend
Version: 0.0.1
Summary: LangChain integration for Ampersend x402 payments
Requires-Dist: langchain-core>=0.3.0
Requires-Dist: ampersend-sdk
Requires-Dist: httpx>=0.27.0
Requires-Python: >=3.13
